geff_spec/__init__.py
geff_spec/_axis.py
geff_spec/_prop_metadata.py
geff_spec/_schema.py
geff_spec/_valid_values.py
geff_spec/utils.py
geff_spec-1.1.0.post0.dist-info/licenses/LICENSE
geff_spec-1.1.0.post0.dist-info/METADATA
geff_spec-1.1.0.post0.dist-info/WHEEL
geff_spec-1.1.0.post0.dist-info/top_level.txt
geff_spec-1.1.0.post0.dist-info/RECORD
