Metadata-Version: 2.4
Name: geff-spec
Version: 1.1.0.post0
Summary: Specification of the Graph Exchange File Format
License-Expression: MIT
Project-URL: repository, https://github.com/live-image-tracking-tools/geff
Project-URL: homepage, https://github.com/live-image-tracking-tools/geff
Project-URL: documentation, https://liveimagetrackingtools.org/geff/
Classifier: Development Status :: 3 - Alpha
Classifier: Natural Language :: English
Classifier: Programming Language :: Python :: 3
Classifier: Programming Language :: Python :: 3.10
Classifier: Programming Language :: Python :: 3.11
Classifier: Programming Language :: Python :: 3.12
Classifier: Programming Language :: Python :: 3.13
Requires-Python: >=3.10
License-File: LICENSE
Requires-Dist: pydantic>=2.11
Requires-Dist: numpy>=1.24
Requires-Dist: numpy>=1.26; python_version >= "3.12"
Requires-Dist: numpy>=2.1; python_version >= "3.13"
Requires-Dist: annotated_types
Dynamic: license-file
